safevitals/__init__.py
safevitals/scanner.py
safevitals/resources/jd-cli.jar
safevitals-1.0.3.dist-info/LICENSE
safevitals-1.0.3.dist-info/METADATA
safevitals-1.0.3.dist-info/WHEEL
safevitals-1.0.3.dist-info/entry_points.txt
safevitals-1.0.3.dist-info/top_level.txt
safevitals-1.0.3.dist-info/RECORD
