Metadata-Version: 2.1
Name: safevitals
Version: 1.0.3
Summary: APK Vulnerability Scanner by Safe Vitals
Home-page: https://github.com/Kavyvachhani/safevitals
Author: Kavy
Author-email: kavyvachhani@gmail.com
Classifier: Programming Language :: Python :: 3
Classifier: License :: OSI Approved :: MIT License
Classifier: Operating System :: OS Independent
Requires-Python: >=3.6
License-File: LICENSE
Requires-Dist: reportlab
Requires-Dist: matplotlib
Requires-Dist: mobsfscan
